MANIFEST.in
setup.py
ovos_ww_plugin_nyumaya_legacy/__init__.py
ovos_ww_plugin_nyumaya_legacy/libnyumaya.py
ovos_ww_plugin_nyumaya_legacy/multi_detector.py
ovos_ww_plugin_nyumaya_legacy/record.py
ovos_ww_plugin_nyumaya_legacy/ringbuffer.py
ovos_ww_plugin_nyumaya_legacy.egg-info/PKG-INFO
ovos_ww_plugin_nyumaya_legacy.egg-info/SOURCES.txt
ovos_ww_plugin_nyumaya_legacy.egg-info/dependency_links.txt
ovos_ww_plugin_nyumaya_legacy.egg-info/entry_points.txt
ovos_ww_plugin_nyumaya_legacy.egg-info/requires.txt
ovos_ww_plugin_nyumaya_legacy.egg-info/top_level.txt
ovos_ww_plugin_nyumaya_legacy.egg-info/zip-safe
ovos_ww_plugin_nyumaya_legacy/lib/armv6/libnyumaya.so
ovos_ww_plugin_nyumaya_legacy/lib/armv7/libnyumaya.so
ovos_ww_plugin_nyumaya_legacy/lib/linux/libnyumaya.so
ovos_ww_plugin_nyumaya_legacy/models/commands/numbers_big_0.3.tflite
ovos_ww_plugin_nyumaya_legacy/models/commands/numbers_labels.txt
ovos_ww_plugin_nyumaya_legacy/models/commands/numbers_small_0.3.tflite
ovos_ww_plugin_nyumaya_legacy/models/commands/on_off_big_0.3.tflite
ovos_ww_plugin_nyumaya_legacy/models/commands/on_off_huge_0.3.tflite
ovos_ww_plugin_nyumaya_legacy/models/commands/on_off_labels.txt
ovos_ww_plugin_nyumaya_legacy/models/commands/subset_big_0.3.tflite
ovos_ww_plugin_nyumaya_legacy/models/commands/subset_labels.txt
ovos_ww_plugin_nyumaya_legacy/models/commands/subset_small_0.3.tflite
ovos_ww_plugin_nyumaya_legacy/models/hotwords/alexa_big_0.3.tflite
ovos_ww_plugin_nyumaya_legacy/models/hotwords/alexa_labels.txt
ovos_ww_plugin_nyumaya_legacy/models/hotwords/alexa_small_0.3.tflite
ovos_ww_plugin_nyumaya_legacy/models/hotwords/marvin_big_0.3.tflite
ovos_ww_plugin_nyumaya_legacy/models/hotwords/marvin_labels.txt
ovos_ww_plugin_nyumaya_legacy/models/hotwords/marvin_sheila_labels.txt
ovos_ww_plugin_nyumaya_legacy/models/hotwords/marvin_sheila_small.tflite
ovos_ww_plugin_nyumaya_legacy/models/hotwords/marvin_small_0.3.tflite
ovos_ww_plugin_nyumaya_legacy/models/hotwords/sheila_big_0.3.tflite
ovos_ww_plugin_nyumaya_legacy/models/hotwords/sheila_labels.txt
ovos_ww_plugin_nyumaya_legacy/models/hotwords/sheila_small_0.3.tflite